{"blocks2image/export_selected_to_SVG":"Izvozi izbrano kot SVG","blocks2image/export_all_to_SVG":"Izvozi vse kot SVG","blocks2image/export_selected_to_PNG":"Izvozi izbrano kot PNG","blocks2image/export_all_to_PNG":"Izvozi vse kot PNG","blocks2image/error_blocks_unselected":"Kliknite bloke, ki jih želite izvoziti!","blocks2image/error_blocks_not_added":"Dodajte bloke v delovni prostor!","blocks2image/@name":"Shrani bloke kot sliko","blocks2image/@description":"Kliknite delovni prostor v urejevalniku z desno miškino tipko, da izvozite bloke kot sliko SVG/PNG."}